odoo/addons/l10n_br_setup_tests/README.rst
odoo/addons/l10n_br_setup_tests/__init__.py
odoo/addons/l10n_br_setup_tests/__manifest__.py
odoo/addons/l10n_br_setup_tests/i18n/l10n_br_setup_tests.pot
odoo/addons/l10n_br_setup_tests/readme/CONTRIBUTORS.rst
odoo/addons/l10n_br_setup_tests/readme/DESCRIPTION.rst
odoo/addons/l10n_br_setup_tests/readme/HISTORY.rst
odoo/addons/l10n_br_setup_tests/static/description/icon.png
odoo/addons/l10n_br_setup_tests/static/description/index.html
odoo/addons/l10n_br_setup_tests/tests/__init__.py
odoo/addons/l10n_br_setup_tests/tests/test_sale_picking.py
odoo14_addon_l10n_br_setup_tests-14.0.1.0.1.dist-info/METADATA
odoo14_addon_l10n_br_setup_tests-14.0.1.0.1.dist-info/WHEEL
odoo14_addon_l10n_br_setup_tests-14.0.1.0.1.dist-info/top_level.txt
odoo14_addon_l10n_br_setup_tests-14.0.1.0.1.dist-info/RECORD
