Metadata-Version: 2.1
Name: odoo14-addon-l10n-br-setup-tests
Version: 14.0.1.0.1
Summary: Modules for Odoo's Brazil-focused usability with integration tests.
Home-page: https://github.com/OCA/l10n-brazil
Author: Engenere, Odoo Community Association (OCA)
Author-email: support@odoo-community.org
License: AGPL-3
Platform: UNKNOWN
Classifier: Programming Language :: Python
Classifier: Framework :: Odoo
Classifier: Framework :: Odoo :: 14.0
Classifier: License :: OSI Approved :: GNU Affero General Public License v3
Classifier: Development Status :: 4 - Beta
Requires-Python: >=3.6
Requires-Dist: odoo14-addon-account-menu
Requires-Dist: odoo14-addon-account-reconciliation-widget
Requires-Dist: odoo14-addon-base-technical-features
Requires-Dist: odoo14-addon-l10n-br-sale-stock
Requires-Dist: odoo14-addon-web-responsive
Requires-Dist: odoo <14.1dev,>=14.0a
